[
          {
                    "id": 1,
                    "first_name": "Berne",
                    "last_name": "Girodon",
                    "email": "bgirodon0@godaddy.com"
          },
          {
                    "id": 2,
                    "first_name": "Calla",
                    "last_name": "Frosch",
                    "email": "cfrosch1@auda.org.au"
          },
          {
                    "id": 3,
                    "first_name": "Delia",
                    "last_name": "Ringer",
                    "email": "dringer2@dion.ne.jp"
          },
          {
                    "id": 4,
                    "first_name": "Anissa",
                    "last_name": "Kliesl",
                    "email": "akliesl3@free.fr"
          },
          {
                    "id": 5,
                    "first_name": "Rock",
                    "last_name": "Priestner",
                    "email": "rpriestner4@unicef.org"
          },
          {
                    "id": 6,
                    "first_name": "Lula",
                    "last_name": "Hamel",
                    "email": "lhamel5@yahoo.com"
          },
          {
                    "id": 7,
                    "first_name": "Biddie",
                    "last_name": "Woollhead",
                    "email": "bwoollhead6@cnet.com"
          },
          {
                    "id": 8,
                    "first_name": "Inglis",
                    "last_name": "Knevett",
                    "email": "iknevett7@homestead.com"
          },
          {
                    "id": 9,
                    "first_name": "Kalle",
                    "last_name": "Goddert.sf",
                    "email": "kgoddertsf8@home.pl"
          },
          {
                    "id": 10,
                    "first_name": "Karoly",
                    "last_name": "Zukerman",
                    "email": "kzukerman9@imageshack.us"
          }
]